<?xml version="1.0" encoding="UTF-8" ?>
<!DOCTYPE generatorConfiguration PUBLIC "-//mybatis.org//DTD MyBatis Generator Configuration 1.0//EN" "http://mybatis.org/dtd/mybatis-generator-config_1_0.dtd" >
<generatorConfiguration>
	
	<context id="context1" targetRuntime="MyBatis3">
		<plugin type="org.mybatis.generator.plugins.SerializablePlugin"></plugin>
		
		<commentGenerator>
			<property name="suppressAllComments" value="true" />
			<property name="suppressDate" value="true" />
		</commentGenerator>
		<jdbcConnection driverClass="com.mysql.jdbc.Driver"
			connectionURL="jdbc:mysql://192.168.1.189:3366/jz_yaya?useUnicode=true&amp;characterEncoding=UTF-8"
			userId="dba" password="mysql" />
		<javaModelGenerator targetPackage="com.jiuzhi.biz.yaya.entity" targetProject="src">
			<property name="trimStrings" value="true" />
		</javaModelGenerator>
		<sqlMapGenerator targetPackage="com.jiuzhi.biz.yaya.provider.dao" targetProject="src" />
		<javaClientGenerator targetPackage="com.jiuzhi.biz.yaya.provider.dao" targetProject="src" type="XMLMAPPER" />
		
		
		
		<table domainObjectName="VideoEpisodeCommentSns" tableName="t_video_episode_comment_sns">
			<generatedKey identity="false" column="commentId" sqlStatement="MySql" />
		</table>
		
		<table domainObjectName="VideoEpisodeCommentPraise" tableName="t_video_episode_comment_praise">
			<generatedKey type="post" identity="true" column="id" sqlStatement="MySql" />
		</table>
				
		<!-- <table domainObjectName="Admin" tableName="tb_admin">
			<generatedKey type="post" identity="true" column="id"
				sqlStatement="MySql" />
		</table>
		<table domainObjectName="FeedBack" tableName="tb_feedback">
			<generatedKey type="post" identity="true" column="id"
				sqlStatement="MySql" />
		</table>

		<table domainObjectName="HospitalRemind" tableName="tb_hospital_remind">
			<generatedKey type="post" identity="true" column="id"
				sqlStatement="MySql" />
		</table>
				
		<table domainObjectName="UIText" tableName="tb_ui_text">
			<generatedKey type="post" identity="true" column="id"
				sqlStatement="MySql" />
		</table>

		<table domainObjectName="UserDevice" tableName="tb_user_device">
			<generatedKey type="post" identity="true" column="id"
				sqlStatement="MySql" />
		</table>

		<table domainObjectName="YeemiaoDeadRule" tableName="tb_yimiao_dead_rule">
			<generatedKey type="post" identity="true" column="id"
				sqlStatement="MySql" />
		</table>


		<table domainObjectName="YeemiaoReplaceRule" tableName="tb_yimiao_replace_rule">
			<generatedKey type="post" identity="true" column="id"
				sqlStatement="MySql" />
		</table>



		
	
		<table domainObjectName="Yeemiao" tableName="tb_yimiao">
			<generatedKey type="post" identity="true" column="id"
				sqlStatement="MySql" />
		</table>
		<table domainObjectName="Version" tableName="tb_version">
			<generatedKey type="post" identity="true" column="id"
				sqlStatement="MySql" />
		</table>
		
		<table domainObjectName="User" tableName="tb_user">
			<generatedKey type="post" identity="true" column="id"
				sqlStatement="MySql" />
		</table>
-->
<!-- 		<table domainObjectName="BabyGrowthRecord" tableName="tb_baby_growth_record">
			<generatedKey type="post" identity="true" column="id"
				sqlStatement="MySql" />
		</table>
		<table domainObjectName="YimiaoRel" tableName="tb_yimiao_rel">
			<generatedKey type="post" identity="true" column="id"
				sqlStatement="MySql" />
		</table>
		<table domainObjectName="YimiaoZcRel" tableName="tb_yimiao_zc_rel">
			<generatedKey type="post" identity="true" column="id"
				sqlStatement="MySql" />
		</table>
		<table domainObjectName="HospitalRel" tableName="tb_hospital_rel">
			<generatedKey type="post" identity="true" column="id"
				sqlStatement="MySql" />
		</table> -->
	
		<!-- <table domainObjectName="Tabloid" tableName="tb_tabloid">
			<generatedKey type="post" identity="true" column="id"
				sqlStatement="MySql" />
				<columnOverride column="context" jdbcType="VARCHAR" />
		</table> -->
		<!--

		<table domainObjectName="HospitalTime" tableName="tb_hospital_time">
			<generatedKey type="post" identity="true" column="id"
				sqlStatement="MySql" />
		</table> -->
		<!-- <table domainObjectName="Huser" tableName="tb_huser">
			<generatedKey type="post" identity="true" column="id"
				sqlStatement="MySql" />
		</table> -->
		
		<!-- <table domainObjectName="AreaExcludeYeemiao" tableName="tb_yimiao_area_exclude">
			<generatedKey type="post" identity="true" column="id"
				sqlStatement="MySql" />
		</table>  -->
		<!-- <table domainObjectName="YeemiaoZhenci" tableName="tb_yimiao_zhenci">
			<generatedKey type="post" identity="true" column="id"
				sqlStatement="MySql" />
		</table> -->
		 <!-- <table domainObjectName="Hospital" tableName="tb_hospital">
			<generatedKey type="post" identity="true" column="id"
				sqlStatement="MySql" />
		</table> -->
			<!-- <table domainObjectName="Area" tableName="tb_area">
			<generatedKey type="post" identity="true" column="id"
				sqlStatement="MySql" />
		</table> -->
		
	<!-- 	<table domainObjectName="Config" tableName="tb_config">
			<generatedKey type="post" identity="true" column="id"
				sqlStatement="MySql" />
		</table> -->
		<!-- <table domainObjectName="ReSendMessage" tableName="tb_resend_message">
			<generatedKey type="post" identity="true" column="id"
				sqlStatement="MySql" />
		</table> -->
			<!-- <table domainObjectName="YeemiaoLog" tableName="tb_yimiao_log">
			<generatedKey type="post" identity="true" column="id"
				sqlStatement="MySql" />
		</table> -->
		<!-- 	<table domainObjectName="UserSetting" tableName="tb_user_setting">
			<generatedKey type="post" identity="true" column="id"
				sqlStatement="MySql" />
		</table> 
		<table domainObjectName="YimiaoComment" tableName="tb_yimiao_comment">
			<generatedKey type="post" identity="true" column="id"
				sqlStatement="MySql" />
		</table>
		-->
		<!-- 	
		<table domainObjectName="YimiaoComment" tableName="tb_yimiao_comment">
			<generatedKey type="post" identity="true" column="id" sqlStatement="MySql" />
		</table> 
		-->
	</context>
</generatorConfiguration>